MANIFEST.in
README.rst
setup.py
wordscrape/__init__.py
wordscrape.egg-info/PKG-INFO
wordscrape.egg-info/SOURCES.txt
wordscrape.egg-info/dependency_links.txt
wordscrape.egg-info/not-zip-safe
wordscrape.egg-info/requires.txt
wordscrape.egg-info/top_level.txt