Metadata-Version: 1.0
Name: wordscrape
Version: 0.3
Summary: Extract data from forms in Microsoft Word documents.
Home-page: http://github.com/Radcliffe/wordscrape
Author: David Radcliffe
Author-email: dradcliffe@gmail.com
License: MIT
Platform: UNKNOWN
